thresult/__init__.py
thresult/result.py
thresult-0.9.24.dist-info/entry_points.txt
thresult-0.9.24.dist-info/LICENSE
thresult-0.9.24.dist-info/WHEEL
thresult-0.9.24.dist-info/METADATA
thresult-0.9.24.dist-info/RECORD
