Metadata-Version: 2.1
Name: thresult
Version: 0.9.24
Summary: Tangled Result
Home-page: https://gitlab.com/tangledlabs/thresult
License: BSD 3-clause
Keywords: thresult,result,tangled,tangledgroup,tangledhub,tangledlabs,tangledcloud
Author: Tangled
Author-email: info@tangledgroup.com
Requires-Python: >=3.10,<4.0
Classifier: Development Status :: 4 - Beta
Classifier: Intended Audience :: Developers
Classifier: License :: OSI Approved :: BSD License
Classifier: License :: Other/Proprietary License
Classifier: Operating System :: OS Independent
Classifier: Programming Language :: Python
Classifier: Programming Language :: Python :: 3
Classifier: Programming Language :: Python :: 3.10
Classifier: Programming Language :: Python :: 3.11
Classifier: Programming Language :: Python :: 3.10
Classifier: Programming Language :: Python :: 3.11
Classifier: Topic :: Software Development :: Libraries :: Python Modules
Project-URL: Repository, https://gitlab.com/tangledlabs/thresult
